[
  {
    "title": "Mastering the Challenges of Celeste: Themes, Tips and Tricks - Airtel",
    "url": "https://www.airtel.in/blog/broadband/mastering-the-challenges-of-celeste-themes-tips-and-tricks/",
    "id": "https://www.airtel.in/blog/broadband/mastering-the-challenges-of-celeste-themes-tips-and-tricks/",
    "published_date": "2024-12-06T06:04:55.000Z",
    "score": null
  },
  {
    "title": "Tips and Tricks - Celeste Guide - IGN",
    "url": "https://www.ign.com/wikis/celeste/Tips_and_Tricks",
    "id": "https://www.ign.com/wikis/celeste/Tips_and_Tricks",
    "published_date": "2018-01-19T21:52:38.000Z",
    "score": null
  },
  {
    "title": "10 Tips To Make YOU 10X BETTER at Celeste - YouTube",
    "url": "https://www.youtube.com/watch?v=rF7C8-xyJWc",
    "id": "https://www.youtube.com/watch?v=rF7C8-xyJWc",
    "published_date": "2024-02-03T00:00:00.000Z",
    "score": null
  },
  {
    "title": "Celeste Movement Techniques Guide - Steam Community",
    "url": "https://steamcommunity.com/sharedfiles/filedetails/?id=2709090843",
    "id": "https://steamcommunity.com/sharedfiles/filedetails/?id=2709090843",
    "published_date": "2025-06-13T07:26:23.000Z",
    "score": null
  },
  {
    "title": "Moves | Celeste Wiki - Fandom",
    "url": "https://celestegame.fandom.com/wiki/Moves",
    "id": "https://celestegame.fandom.com/wiki/Moves",
    "published_date": "2024-10-29T22:04:34.000Z",
    "score": null
  },
  {
    "title": "need good advice to get good good :: Celeste General",
    "url": "https://steamcommunity.com/app/504230/discussions/0/3826410862742329626/",
    "id": "https://steamcommunity.com/app/504230/discussions/0/3826410862742329626/",
    "published_date": "2023-03-27T00:00:00.000Z",
    "score": null
  },
  {
    "title": "Celeste Beginner's Guide: How to become a pro",
    "url": "https://game.dazepuzzle.com/celeste-beginners-guide/",
    "id": "https://game.dazepuzzle.com/celeste-beginners-guide/",
    "published_date": "2025-03-26T08:04:08.000Z",
    "score": null
  },
  {
    "title": "Spo\u0142eczno\u015b\u0107 Steam :: Poradnik :: Celeste Movement Techniques Guide",
    "url": "https://steamcommunity.com/sharedfiles/filedetails/?l=polish&id=2709090843",
    "id": "https://steamcommunity.com/sharedfiles/filedetails/?l=polish&id=2709090843",
    "published_date": "2025-06-14T14:52:46.000Z",
    "score": null
  },
  {
    "title": "8 Things We Wish We Knew Before Playing Celeste - TheGamer",
    "url": "https://www.thegamer.com/things-we-wish-we-knew-before-playing-celeste/",
    "id": "https://www.thegamer.com/things-we-wish-we-knew-before-playing-celeste/",
    "published_date": "2022-05-31T01:45:13.000Z",
    "score": null
  },
  {
    "title": "Steam Community :: Guide :: How to become a successful Celeste Player",
    "url": "https://steamcommunity.com/sharedfiles/filedetails/?id=3145962595",
    "id": "https://steamcommunity.com/sharedfiles/filedetails/?id=3145962595",
    "published_date": "2025-10-28T12:49:29.000Z",
    "score": null
  }
]
